<?xml version="1.0" encoding="utf-8"?>
<!DOCTYPE hibernate-mapping PUBLIC "-//Hibernate/Hibernate Mapping DTD 3.0//EN"
        "http://hibernate.sourceforge.net/hibernate-mapping-3.0.dtd">
<!-- 
    Mapping file autogenerated by MyEclipse Persistence Tools
-->
<hibernate-mapping>
    <class name="com.orient.metamodel.metadomain.Column" table="CWM_TAB_COLUMNS">
        <id name="id" type="java.lang.String">
            <column name="ID" length="38"/>
            <generator class="sequence">
                <param name="sequence">SEQ_CWM_TAB_COLUMNS</param>
            </generator>
        </id>
        <many-to-one name="table" class="com.orient.metamodel.metadomain.Table" fetch="select" lazy="false">
            <column name="TABLE_ID" length="38"/>
        </many-to-one>
        <many-to-one name="restriction" class="com.orient.metamodel.metadomain.Restriction" fetch="select" lazy="false">
            <column name="RESTRICTION_ID" length="38"/>
        </many-to-one>
        <many-to-one name="view" class="com.orient.metamodel.metadomain.View" fetch="select" lazy="false">
            <column name="REF_VIEW_ID" length="38"/>
        </many-to-one>
        <!-- <property name="viewid" type="java.lang.String">
            <column name="REF_VIEW_ID" length="38"></column>
        </property> -->
        <property name="name" type="java.lang.String">
            <column name="S_NAME" length="50" not-null="true"/>
        </property>
        <property name="displayName" type="java.lang.String">
            <column name="DISPLAY_NAME" length="100" not-null="true"/>
        </property>
        <property name="category" type="java.lang.Long">
            <column name="CATEGORY" precision="1" scale="0" not-null="true"/>
        </property>
        <property name="description" type="java.lang.String">
            <column name="DESCRIPTION" length="2000"/>
        </property>
        <property name="columnName" type="java.lang.String">
            <column name="S_COLUMN_NAME" length="50"/>
        </property>
        <property name="isAllSearch" type="java.lang.String">
            <column name="IS_WHO_SEARCH" length="10"/>
        </property>
        <property name="isForSearch" type="java.lang.String">
            <column name="IS_FOR_SEARCH" length="10"/>
        </property>
        <property name="isIndex" type="java.lang.String">
            <column name="IS_INDEX" length="10"/>
        </property>
        <property name="operateSign" type="java.lang.String">
            <column name="OPERATE_SIGN" length="10"/>
        </property>
        <property name="purpose" type="java.lang.String">
            <column name="PURPOSE" length="10"/>
        </property>
        <property name="casesensitive" type="java.lang.String">
            <column name="CASESENSITIVE" length="15"/>
        </property>
        <property name="defaultValue" type="java.lang.String">
            <column name="DEFAULT_VALUE" length="30"/>
        </property>
        <property name="isNull" type="java.lang.String">
            <column name="IS_NULLABLE" length="10"/>
        </property>
        <property name="isNeed" type="java.lang.String">
            <column name="IS_NEED" length="10"/>
        </property>
        <property name="isOnly" type="java.lang.String">
            <column name="IS_ONLY" length="10"/>
        </property>
        <property name="isPK" type="java.lang.Long">
            <column name="IS_PK" precision="10" scale="0"/>
        </property>
        <property name="isAutoIncrement" type="java.lang.String">
            <column name="IS_AUTOINCREMENT" length="10"/>
        </property>
        <property name="type" type="java.lang.String">
            <column name="TYPE" length="20"/>
        </property>
        <property name="sequenceName" type="java.lang.String">
            <column name="SEQUENCE_NAME" length="30"/>
        </property>
        <property name="maxLength" type="java.lang.Long">
            <column name="MAX_LENGTH" precision="38" scale="0"/>
        </property>
        <property name="minLength" type="java.lang.Long">
            <column name="MIN_LENGTH" precision="38" scale="0"/>
        </property>
        <property name="numlength" type="java.lang.Long">
            <column name="NUM_LENGTH" precision="38" scale="0"/>
        </property>
        <property name="numprecision" type="java.lang.Long">
            <column name="NUM_PRECISION" precision="38" scale="0"/>
        </property>
        <property name="isShow" type="java.lang.String">
            <column name="IS_SHOW" length="10"/>
        </property>
        <property name="isWrap" type="java.lang.String">
            <column name="IS_WRAP" length="10"/>
        </property>
        <property name="propertyParagraph" type="java.lang.String">
            <column name="PROPERTY_PARAGRAPH" length="30"/>
        </property>
        <property name="propertyCategory" type="java.lang.String">
            <column name="PROPERTY_CATEGORY" length="30"/>
        </property>
        <property name="linage" type="java.lang.Long">
            <column name="LINAGE" precision="38" scale="0"/>
        </property>
        <property name="isValid" type="java.lang.Long">
            <column name="IS_VALID" precision="1" scale="0" not-null="true"/>
        </property>
        <property name="isMutiUk" type="java.lang.Long">
            <column name="IS_MUTI_UK" precision="10" scale="0"/>
        </property>
        <property name="isUsedPaixu" type="java.lang.Long">
            <column name="IS_USED_PAIXU" precision="10" scale="0"/>
        </property>
        <property name="order" type="java.lang.Long">
            <column name="ORDER_SIGN" precision="10" scale="0"/>
        </property>
        <property name="cite" type="java.lang.String">
            <column name="CITE" length="100"/>
        </property>
        <property name="arithId" type="java.lang.String">
            <column name="ARITH_ID" length="100"/>
        </property>
        <property name="arithName" type="java.lang.String">
            <column name="ARITH_NAME" length="100"/>
        </property>
        <property name="arithMethod" type="java.lang.String">
            <column name="ARITH_METHOD" length="100"/>
        </property>
        <property name="arithType" type="java.lang.String">
            <column name="ARITH_TYPE" length="100"/>
        </property>
        <property name="mapColumn" type="java.lang.String">
            <column name="MAP_COLUMN" length="38"/>
        </property>
        <property name="autoAddDefault" type="java.lang.Long">
            <column name="SEQ_VALUE" precision="38" scale="0"/>
        </property>
        <property name="editable" type="java.lang.String">
            <column name="EDITABLE" length="10"/>
        </property>
        <property name="seqInterval" type="java.lang.Long">
            <column name="SEQ_INTERVAL" precision="38" scale="0"/>
        </property>
        <property name="selector" type="java.lang.String">
            <column name="SELECTOR" length="200"/>
        </property>
        <property name="unit" type="java.lang.String">
            <column name="UNIT" length="100"/>
        </property>
        <set name="arithAttribute" inverse="true" lazy="false">
            <key>
                <column name="ARITH_COLUMN_ID" length="38"/>
            </key>
            <one-to-many class="com.orient.metamodel.metadomain.ArithAttribute"/>
        </set>
        <set name="cwmViewPaixuColumns" inverse="true" lazy="false">
            <key>
                <column name="PAIXU_COLUMN_ID" length="38"/>
            </key>
            <one-to-many class="com.orient.metamodel.metadomain.ViewSortColumn"/>
        </set>
        <set name="cwmViewReturnColumns" inverse="true" lazy="false">
            <key>
                <column name="RETURN_COLUMN_ID" length="38" not-null="true"/>
            </key>
            <one-to-many class="com.orient.metamodel.metadomain.ViewResultColumn"/>
        </set>
        <set name="columnSet" inverse="true" lazy="false">
            <key>
                <column name="COLUMN_ID" length="38" not-null="true"/>
            </key>
            <one-to-many class="com.orient.metamodel.metadomain.TableColumn"/>
        </set>
        <set name="cwmTableEnums" inverse="true" lazy="false">
            <key>
                <column name="COLUMN_ID" length="38" not-null="true"/>
            </key>
            <one-to-many class="com.orient.metamodel.metadomain.TableEnum"/>
        </set>

        <one-to-one name="relationColumn" class="com.orient.metamodel.metadomain.RelationColumns"
                    cascade="all" property-ref="cwmTabColumnsByColumnId"/>

    </class>
</hibernate-mapping>
